matchmaker/__init__.py
matchmaker/decorators.py
matchmaker-0.1.4.dist-info/METADATA
matchmaker-0.1.4.dist-info/WHEEL
matchmaker-0.1.4.dist-info/top_level.txt
matchmaker-0.1.4.dist-info/RECORD
