Metadata-Version: 2.1
Name: matchmaker
Version: 0.1.4
Summary: Easy creation of hamcrest matchers
Home-page: https://github.com/txels/matchmaker
Author: Carles Barrobés
Author-email: carles@barrobes.com
License: UNKNOWN
Platform: UNKNOWN
Classifier: Development Status :: 4 - Beta
Classifier: Intended Audience :: Developers
Classifier: License :: OSI Approved :: GNU Library or Lesser General Public License (LGPL)
Classifier: Operating System :: OS Independent
Classifier: Programming Language :: Python
Classifier: Topic :: Software Development :: Testing
Requires-Dist: PyHamcrest
